{
 "description": "We repect your choice . Once the sale starts tomorrow, you can place a request to trade these NFT's from @entitled, being my co-founder he will claim your giveaways and trade with you for 1 miota :)",
 "issuerName": "Soonaverse",
 "name": "Giveaway Winner - Common NFT Pass",
 "soonaverseId": "0x275da6e9db494d39d477f7281632bee2f4dcbba4",
 "standard": "IRC27",
 "type": "image/png",
 "uri": "ipfs://bafkreidv6htyybikaiou5lojw5tq7git3bgkv4247pyb3s5bsjbijchox4",
 "version": "v1.0"
}