{
 "description": "\nEstilo musical de origen jamaicano derivado del rock cuyas canciones se caracterizan por el ritmo alegre, repetitivo y marcado, las melodías suaves y las letras comprometidas en favor de la paz, de la ayuda al Tercer Mundo, etc.",
 "issuerName": "Soonaverse",
 "name": "reggae pioneers",
 "soonaverseId": "0x817a8be9b477047351cb65e3dda1229a04642f2e",
 "standard": "IRC27",
 "type": "image/png",
 "uri": "ipfs://bafkreianq3fbo27njc232oxiybir7smiozgz3flihoqnmg5z65iqp7kfri",
 "version": "v1.0"
}