{
 "description": "To celebrate the upcoming presale  of REKT-REX: THE OG COLLECTION, REKT-Collectibles will be giving away 5000 Free REKT-REX Concept NFTs.  \nTo qualify:\n1) Join Space\n2) Follow/retweet  us on twitter @RektcollectNFT \n- Retweet with your soonaverse profile id.\n\nNote: This NFT does not double as a REKT- Museum Membership.\n",
 "issuerName": "Soonaverse",
 "name": "REKT-REX Concept NFT Free Airdrop for Early Members",
 "soonaverseId": "0x1271fb0a502c43866ef06ecfc33aa5b6cba283db",
 "standard": "IRC27",
 "type": "image/png",
 "uri": "ipfs://bafkreialqxx43hpmzhbfqxwxiqaiouqidcqpskoq2tyztra4iqdlpfovt4",
 "version": "v1.0"
}