{
 "description": "The tenth collection. The special collection. This is art. This is satire.\n\nThis is one of the first \"Art Satire\" - Projects in the Cryptospace.\n\nThis \"Renkert Snofla\"-Collection again shows the development from the Basic picture without many effects to the final picture of this collection wich has lots of artefacts and effects.\n\n24 Steps - 24 beautiful unique pictures. But wait.. Every picture contains 9 RENKERT! 9 Pictures in one!\n\nYes this was a lot of work!\n\nCheck out the details of the final version!\n\nThe way of creation is the artists secret.\n\nThis is the tenth collection. Others will follow. Maybe. Or not?! Every collection could be the final one!",
 "issuerName": "Soonaverse",
 "name": "Renkert Snofla - The tenth collection",
 "royalties": {
  "smr1qr3je96rk2fsk765gj6qm799d5d22l5qrgq93qhs3j5jqchaqqew2r7lf04": 0.15
 },
 "soonaverseId": "0x1c712fbf1033a8f71f2c59728d9e65cc75e7a92e",
 "standard": "IRC27",
 "type": "image/jpeg",
 "uri": "ipfs://bafybeicfjt2ttxjv6qprfrdtx64theiggrirwghad7xef2jven5dkzsd7i",
 "version": "v1.0"
}